{
    "1": {
        "start": "2024-08-11T13:10:21.824557",
        "block1": {
            "start": "2024-08-11T13:10:21.824934",
            "end": "2024-08-11T13:12:20.933015",
            "duration": "119.11"
        },
        "end": "2024-08-11T13:12:47.812688",
        "duration": "145.99"
    },
    "2": {
        "start": "2024-08-11T13:12:47.814592",
        "block1": {
            "start": "2024-08-11T13:12:47.815113",
            "end": "2024-08-11T13:14:42.663068",
            "duration": "114.85"
        },
        "end": "2024-08-11T13:15:09.841844",
        "duration": "142.03"
    },
    "3": {
        "start": "2024-08-11T13:15:09.843341",
        "block1": {
            "start": "2024-08-11T13:15:09.844077",
            "end": "2024-08-11T13:17:07.264102",
            "duration": "117.42"
        },
        "end": "2024-08-11T13:17:31.852076",
        "duration": "142.01"
    },
    "4": {
        "start": "2024-08-11T13:17:31.852855",
        "block1": {
            "start": "2024-08-11T13:17:31.853812",
            "end": "2024-08-11T13:19:26.714985",
            "duration": "114.86"
        },
        "end": "2024-08-11T13:19:53.862236",
        "duration": "142.01"
    },
    "5": {
        "start": "2024-08-11T13:19:53.863014",
        "block1": {
            "start": "2024-08-11T13:19:53.863919",
            "end": "2024-08-11T13:21:48.633433",
            "duration": "114.77"
        },
        "end": "2024-08-11T13:22:15.872327",
        "duration": "142.01"
    }
}