{
    "1": {
        "start": "2024-08-19T14:53:52.137332",
        "block1": {
            "start": "2024-08-19T14:53:52.137594",
            "end": "2024-08-19T14:57:55.931839",
            "duration": "243.79"
        },
        "end": "2024-08-19T14:58:14.444096",
        "duration": "262.31"
    },
    "2": {
        "start": "2024-08-19T14:58:14.445150",
        "block1": {
            "start": "2024-08-19T14:58:14.452446",
            "end": "2024-08-19T15:02:17.015297",
            "duration": "242.56"
        },
        "end": "2024-08-19T15:02:36.490327",
        "duration": "262.05"
    },
    "3": {
        "start": "2024-08-19T15:02:36.490881",
        "block1": {
            "start": "2024-08-19T15:02:36.494623",
            "end": "2024-08-19T15:06:41.232157",
            "duration": "244.74"
        },
        "end": "2024-08-19T15:06:58.742258",
        "duration": "262.25"
    },
    "4": {
        "start": "2024-08-19T15:06:58.742902",
        "block1": {
            "start": "2024-08-19T15:06:58.752832",
            "end": "2024-08-19T15:11:01.121887",
            "duration": "242.37"
        },
        "end": "2024-08-19T15:11:21.015227",
        "duration": "262.27"
    },
    "5": {
        "start": "2024-08-19T15:11:21.015816",
        "block1": {
            "start": "2024-08-19T15:11:21.025310",
            "end": "2024-08-19T15:15:14.562801",
            "duration": "233.54"
        },
        "end": "2024-08-19T15:15:15.256411",
        "duration": "234.24"
    }
}