{
    "1": {
        "start": "2024-09-02T09:51:09.088692",
        "block1": {
            "start": "2024-09-02T09:51:13.110032",
            "end": "2024-09-02T10:36:11.084987",
            "duration": "2697.97"
        },
        "end": "2024-09-02T10:36:11.202394",
        "duration": "2702.11"
    },
    "2": {
        "start": "2024-09-02T10:36:11.205260",
        "block1": {
            "start": "2024-09-02T10:36:14.721833",
            "end": "2024-09-02T11:21:12.540043",
            "duration": "2697.82"
        },
        "end": "2024-09-02T11:21:36.651886",
        "duration": "2725.45"
    },
    "3": {
        "start": "2024-09-02T11:21:36.653531",
        "block1": {
            "start": "2024-09-02T11:21:39.206014",
            "end": "2024-09-02T12:06:37.043095",
            "duration": "2697.84"
        },
        "end": "2024-09-02T12:07:01.132309",
        "duration": "2724.48"
    },
    "4": {
        "start": "2024-09-02T12:07:01.134013",
        "block1": {
            "start": "2024-09-02T12:07:03.768665",
            "end": "2024-09-02T12:52:01.506063",
            "duration": "2697.74"
        },
        "end": "2024-09-02T12:52:01.511723",
        "duration": "2700.38"
    },
    "5": {
        "start": "2024-09-02T12:52:01.512752",
        "block1": {
            "start": "2024-09-02T12:52:04.163411",
            "end": "2024-09-02T13:37:01.861647",
            "duration": "2697.70"
        },
        "end": "2024-09-02T13:37:01.866670",
        "duration": "2700.35"
    }
}