{
    "start": "2024-08-05T23:18:46.445106",
    "num_accelerators": 33,
    "num_hosts": 3,
    "hostname": "client1",
    "metric": {
        "train_au_percentage": [
            74.95740069059322,
            70.20911466662582,
            70.49950175059398,
            71.07141860472409,
            68.50079349126392
        ],
        "train_au_mean_percentage": 71.04764584076023,
        "train_au_meet_expectation": "success",
        "train_au_stdev_percentage": 2.134329004338991,
        "train_throughput_samples_per_second": [
            7020.753470549968,
            6577.49234024124,
            6604.0349149405465,
            6656.3438027532275,
            6416.994804468498
        ],
        "train_throughput_mean_samples_per_second": 6655.123866590696,
        "train_throughput_stdev_samples_per_second": 199.51374921388768,
        "train_io_mean_MB_per_second": 17951.893505971577,
        "train_io_stdev_MB_per_second": 538.1792511548923
    },
    "num_files_train": 2915459,
    "num_files_eval": 0,
    "num_samples_per_file": 1,
    "host_cpu_count": [
        672,
        0,
        0
    ],
    "host_processor_name": "x86_64",
    "potential_caching": [
        0,
        0,
        0
    ],
    "host_cpuinfo": {
        "vendor_id": "GenuineIntel",
        "cpu family": "6",
        "model": "143",
        "model name": "Genuine Intel(R) CPU 0000%@",
        "stepping": "3",
        "microcode": "0x8d0002a0",
        "cpu MHz": "1900.000",
        "cache size": "107520 KB",
        "physical id": "1",
        "siblings": "112",
        "core id": "55",
        "cpu cores": "56",
        "apicid": "239",
        "initial apicid": "239",
        "fpu": "yes",
        "fpu_exception": "yes",
        "cpuid level": "32",
        "wp": "yes",
        "flags": "fpu vme de pse tsc msr pae mce cx8 apic sep mtrr pge mca cmov pat pse36 clflush dts acpi mmx fxsr sse sse2 ss ht tm pbe syscall nx pdpe1gb rdtscp lm constant_tsc art arch_perfmon pebs bts rep_good nopl xtopology nonstop_tsc cpuid aperfmperf tsc_known_freq pni pclmulqdq dtes64 monitor ds_cpl vmx smx est tm2 ssse3 sdbg fma cx16 xtpr pdcm pcid sse4_1 sse4_2 x2apic movbe popcnt tsc_deadline_timer aes xsave avx f16c rdrand lahf_lm abm 3dnowprefetch cpuid_fault epb cat_l3 cat_l2 cdp_l3 invpcid_single intel_ppin cdp_l2 ssbd mba ibrs ibpb stibp ibrs_enhanced tpr_shadow vnmi flexpriority ept vpid ept_ad fsgsbase tsc_adjust bmi1 avx2 smep bmi2 erms invpcid cqm rdt_a avx512f avx512dq rdseed adx smap avx512ifma clflushopt clwb intel_pt avx512cd sha_ni avx512bw avx512vl xsaveopt xsavec xgetbv1 xsaves cqm_llc cqm_occup_llc cqm_mbm_total cqm_mbm_local split_lock_detect avx_vnni avx512_bf16 wbnoinvd dtherm arat pln pts hwp hwp_act_window hwp_epp hwp_pkg_req avx512vbmi umip pku ospke waitpkg avx512_vbmi2 gfni vaes vpclmulqdq avx512_vnni avx512_bitalg tme avx512_vpopcntdq la57 rdpid bus_lock_detect cldemote movdiri movdir64b enqcmd fsrm avx512_vp2intersect md_clear serialize tsxldtrk pconfig arch_lbr amx_bf16 avx512_fp16 amx_tile amx_int8 flush_l1d arch_capabilities",
        "vmx flags": "vnmi preemption_timer posted_intr invvpid ept_x_only ept_ad ept_1gb flexpriority apicv tsc_offset vtpr mtf vapic ept vpid unrestricted_guest vapic_reg vid ple shadow_vmcs pml ept_mode_based_exec tsc_scaling usr_wait_pause",
        "bugs": "spectre_v1 spectre_v2 spec_store_bypass swapgs mmio_unknown eibrs_pbrsb bhi",
        "bogomips": "3788.80",
        "clflush size": "64",
        "cache_alignment": "64",
        "address sizes": "46 bits physical, 57 bits virtual",
        "power management": ""
    },
    "host_meminfo": {
        "MemTotal": "527999968 kB",
        "MemFree": "515752176 kB",
        "MemAvailable": "513996400 kB",
        "Buffers": "16712 kB",
        "Cached": "479264 kB",
        "SwapCached": "6928 kB",
        "Active": "95868 kB",
        "Inactive": "2636648 kB",
        "Active(anon)": "7812 kB",
        "Inactive(anon)": "2256352 kB",
        "Active(file)": "88056 kB",
        "Inactive(file)": "380296 kB",
        "Unevictable": "39596 kB",
        "Mlocked": "27824 kB",
        "SwapTotal": "8388604 kB",
        "SwapFree": "8306696 kB",
        "Dirty": "40 kB",
        "Writeback": "0 kB",
        "AnonPages": "2273548 kB",
        "Mapped": "358128 kB",
        "Shmem": "6544 kB",
        "KReclaimable": "393832 kB",
        "Slab": "1486584 kB",
        "SReclaimable": "393832 kB",
        "SUnreclaim": "1092752 kB",
        "KernelStack": "51280 kB",
        "PageTables": "23112 kB",
        "NFS_Unstable": "0 kB",
        "Bounce": "0 kB",
        "WritebackTmp": "0 kB",
        "CommitLimit": "272388588 kB",
        "Committed_AS": "31856504 kB",
        "VmallocTotal": "13743895347199 kB",
        "VmallocUsed": "366272 kB",
        "VmallocChunk": "0 kB",
        "Percpu": "333312 kB",
        "HardwareCorrupted": "0 kB",
        "AnonHugePages": "0 kB",
        "ShmemHugePages": "0 kB",
        "ShmemPmdMapped": "0 kB",
        "FileHugePages": "0 kB",
        "FilePmdMapped": "0 kB",
        "HugePages_Total": "0",
        "HugePages_Free": "0",
        "HugePages_Rsvd": "0",
        "HugePages_Surp": "0",
        "Hugepagesize": "2048 kB",
        "Hugetlb": "0 kB",
        "DirectMap4k": "561928 kB",
        "DirectMap2M": "15915008 kB",
        "DirectMap1G": "522190848 kB"
    },
    "host_memory_GB": [
        1510.6202850341797,
        0.0,
        0.0
    ],
    "data_size_per_host_GB": 2559.997547449544,
    "epochs": 5,
    "end": "2024-08-06T00:00:20.484961"
}