{
    "start": "2024-07-18T03:59:56.444635",
    "num_accelerators": 12,
    "num_hosts": 3,
    "hostname": "node-02",
    "metric": {
        "train_au_percentage": [
            94.11611208569481,
            90.33833766994378,
            94.47764596258482,
            94.62247091005912,
            94.80068542146974
        ],
        "train_au_mean_percentage": 93.67105040995045,
        "train_au_meet_expectation": "success",
        "train_au_stdev_percentage": 1.6814830784415211,
        "train_throughput_samples_per_second": [
            230.89473917968215,
            222.82502217576874,
            235.30317853372566,
            235.7122940986876,
            236.3310699364509
        ],
        "train_throughput_mean_samples_per_second": 232.213260784863,
        "train_throughput_stdev_samples_per_second": 5.0719759746968185,
        "train_io_mean_MB_per_second": 32465.562687863054,
        "train_io_stdev_MB_per_second": 709.1091757692964
    },
    "num_files_train": 42000,
    "num_files_eval": 0,
    "num_samples_per_file": 1,
    "host_cpu_count": [
        192,
        192,
        192
    ],
    "host_processor_name": "x86_64",
    "potential_caching": [
        0,
        0,
        0
    ],
    "host_cpuinfo": {
        "vendor_id": "AuthenticAMD",
        "cpu family": "23",
        "model": "49",
        "model name": "AMD EPYC 7642 48-Core Processor",
        "stepping": "0",
        "microcode": "0x830107a",
        "cpu MHz": "2295.644",
        "cache size": "512 KB",
        "physical id": "1",
        "siblings": "96",
        "core id": "62",
        "cpu cores": "48",
        "apicid": "253",
        "initial apicid": "253",
        "fpu": "yes",
        "fpu_exception": "yes",
        "cpuid level": "16",
        "wp": "yes",
        "flags": "fpu vme de pse tsc msr pae mce cx8 apic sep mtrr pge mca cmov pat pse36 clflush mmx fxsr sse sse2 ht syscall nx mmxext fxsr_opt pdpe1gb rdtscp lm constant_tsc rep_good nopl nonstop_tsc cpuid extd_apicid aperfmperf rapl pni pclmulqdq monitor ssse3 fma cx16 sse4_1 sse4_2 x2apic movbe popcnt aes xsave avx f16c rdrand lahf_lm cmp_legacy svm extapic cr8_legacy abm sse4a misalignsse 3dnowprefetch osvw ibs skinit wdt tce topoext perfctr_core perfctr_nb bpext perfctr_llc mwaitx cpb cat_l3 cdp_l3 hw_pstate ssbd mba ibrs ibpb stibp vmmcall fsgsbase bmi1 avx2 smep bmi2 cqm rdt_a rdseed adx smap clflushopt clwb sha_ni xsaveopt xsavec xgetbv1 cqm_llc cqm_occup_llc cqm_mbm_total cqm_mbm_local clzero irperf xsaveerptr rdpru wbnoinvd amd_ppin arat npt lbrv svm_lock nrip_save tsc_scale vmcb_clean flushbyasid decodeassists pausefilter pfthreshold avic v_vmsave_vmload vgif v_spec_ctrl umip rdpid overflow_recov succor smca sme sev sev_es",
        "bugs": "sysret_ss_attrs spectre_v1 spectre_v2 spec_store_bypass retbleed smt_rsb srso",
        "bogomips": "4558.84",
        "TLB size": "3072 4K pages",
        "clflush size": "64",
        "cache_alignment": "64",
        "address sizes": "43 bits physical, 48 bits virtual",
        "power management": "ts ttp tm hwpstate cpb eff_freq_ro [13] [14]"
    },
    "host_meminfo": {
        "MemTotal": "263900568 kB",
        "MemFree": "230018620 kB",
        "MemAvailable": "252504480 kB",
        "Buffers": "542996 kB",
        "Cached": "20202700 kB",
        "SwapCached": "23112 kB",
        "Active": "10180344 kB",
        "Inactive": "11789116 kB",
        "Active(anon)": "8280 kB",
        "Inactive(anon)": "1249072 kB",
        "Active(file)": "10172064 kB",
        "Inactive(file)": "10540044 kB",
        "Unevictable": "36840 kB",
        "Mlocked": "36840 kB",
        "SwapTotal": "8388604 kB",
        "SwapFree": "8283292 kB",
        "Dirty": "9768 kB",
        "Writeback": "0 kB",
        "AnonPages": "1240300 kB",
        "Mapped": "474684 kB",
        "Shmem": "24268 kB",
        "KReclaimable": "3889496 kB",
        "Slab": "5711384 kB",
        "SReclaimable": "3889496 kB",
        "SUnreclaim": "1821888 kB",
        "KernelStack": "38048 kB",
        "PageTables": "12912 kB",
        "NFS_Unstable": "0 kB",
        "Bounce": "0 kB",
        "WritebackTmp": "0 kB",
        "CommitLimit": "140338888 kB",
        "Committed_AS": "12643724 kB",
        "VmallocTotal": "34359738367 kB",
        "VmallocUsed": "2767624 kB",
        "VmallocChunk": "0 kB",
        "Percpu": "231424 kB",
        "HardwareCorrupted": "0 kB",
        "AnonHugePages": "0 kB",
        "ShmemHugePages": "0 kB",
        "ShmemPmdMapped": "0 kB",
        "FileHugePages": "0 kB",
        "FilePmdMapped": "0 kB",
        "HugePages_Total": "0",
        "HugePages_Free": "0",
        "HugePages_Rsvd": "0",
        "HugePages_Surp": "0",
        "Hugepagesize": "2048 kB",
        "Hugetlb": "0 kB",
        "DirectMap4k": "3023760 kB",
        "DirectMap2M": "44011520 kB",
        "DirectMap1G": "222298112 kB"
    },
    "host_memory_GB": [
        251.6751937866211,
        251.67240524291992,
        251.67530822753906
    ],
    "data_size_per_host_GB": 1911.4546403288841,
    "epochs": 5,
    "end": "2024-07-18T04:15:20.211114"
}