{
    "start": "2024-09-09T10:27:25.720352",
    "num_accelerators": 130,
    "num_hosts": 5,
    "hostname": "ip-172-26-4-91",
    "metric": {
        "train_au_percentage": [
            89.72406162391735,
            91.30366921615095,
            91.45057382683962,
            91.86866065421476,
            92.87985940927238
        ],
        "train_au_mean_percentage": 91.44536494607901,
        "train_au_meet_expectation": "success",
        "train_au_stdev_percentage": 1.021757658220577,
        "train_throughput_samples_per_second": [
            207928.9691377723,
            211816.32730578852,
            212159.19572719117,
            213111.6060221259,
            215440.8286509423
        ],
        "train_throughput_mean_samples_per_second": 212091.38536876402,
        "train_throughput_stdev_samples_per_second": 2435.799028853427,
        "train_io_mean_MB_per_second": 23191.845982341252,
        "train_io_stdev_MB_per_second": 266.3506385367069
    },
    "num_files_train": 47908,
    "num_files_eval": 0,
    "num_samples_per_file": 1251,
    "host_cpu_count": [
        640,
        0,
        0,
        0,
        0
    ],
    "host_processor_name": "x86_64",
    "potential_caching": [
        0,
        0,
        0,
        0,
        0
    ],
    "host_cpuinfo": {
        "vendor_id": "GenuineIntel",
        "cpu family": "6",
        "model": "106",
        "model name": "Intel(R) Xeon(R) Platinum 8375C CPU @ 2.90GHz",
        "stepping": "6",
        "microcode": "0xd0003e8",
        "cpu MHz": "3499.473",
        "cache size": "55296 KB",
        "physical id": "1",
        "siblings": "64",
        "core id": "31",
        "cpu cores": "32",
        "apicid": "127",
        "initial apicid": "127",
        "fpu": "yes",
        "fpu_exception": "yes",
        "cpuid level": "27",
        "wp": "yes",
        "flags": "fpu vme de pse tsc msr pae mce cx8 apic sep mtrr pge mca cmov pat pse36 clflush mmx fxsr sse sse2 ss ht syscall nx pdpe1gb rdtscp lm constant_tsc arch_perfmon rep_good nopl xtopology nonstop_tsc cpuid aperfmperf tsc_known_freq pni pclmulqdq monitor ssse3 fma cx16 pcid sse4_1 sse4_2 x2apic movbe popcnt tsc_deadline_timer aes xsave avx f16c rdrand hypervisor lahf_lm abm 3dnowprefetch invpcid_single ssbd ibrs ibpb stibp ibrs_enhanced fsgsbase tsc_adjust bmi1 avx2 smep bmi2 erms invpcid avx512f avx512dq rdseed adx smap avx512ifma clflushopt clwb avx512cd sha_ni avx512bw avx512vl xsaveopt xsavec xgetbv1 xsaves wbnoinvd ida arat avx512vbmi pku ospke avx512_vbmi2 gfni vaes vpclmulqdq avx512_vnni avx512_bitalg tme avx512_vpopcntdq rdpid md_clear flush_l1d arch_capabilities",
        "bugs": "apic_c1e spectre_v1 spectre_v2 spec_store_bypass swapgs mmio_stale_data eibrs_pbrsb gds bhi",
        "bogomips": "5799.89",
        "clflush size": "64",
        "cache_alignment": "64",
        "address sizes": "46 bits physical, 48 bits virtual",
        "power management": ""
    },
    "host_meminfo": {
        "MemTotal": "259883840 kB",
        "MemFree": "252933760 kB",
        "MemAvailable": "252111124 kB",
        "Buffers": "18800 kB",
        "Cached": "495648 kB",
        "SwapCached": "0 kB",
        "Active": "5526124 kB",
        "Inactive": "76468 kB",
        "Active(anon)": "5113220 kB",
        "Inactive(anon)": "4 kB",
        "Active(file)": "412904 kB",
        "Inactive(file)": "76464 kB",
        "Unevictable": "35472 kB",
        "Mlocked": "27616 kB",
        "SwapTotal": "0 kB",
        "SwapFree": "0 kB",
        "Zswap": "0 kB",
        "Zswapped": "0 kB",
        "Dirty": "16 kB",
        "Writeback": "0 kB",
        "AnonPages": "5127216 kB",
        "Mapped": "354812 kB",
        "Shmem": "8048 kB",
        "KReclaimable": "106776 kB",
        "Slab": "495996 kB",
        "SReclaimable": "106776 kB",
        "SUnreclaim": "389220 kB",
        "KernelStack": "48880 kB",
        "PageTables": "49688 kB",
        "SecPageTables": "0 kB",
        "NFS_Unstable": "0 kB",
        "Bounce": "0 kB",
        "WritebackTmp": "0 kB",
        "CommitLimit": "129941920 kB",
        "Committed_AS": "73805648 kB",
        "VmallocTotal": "34359738367 kB",
        "VmallocUsed": "297700 kB",
        "VmallocChunk": "0 kB",
        "Percpu": "78336 kB",
        "HardwareCorrupted": "0 kB",
        "AnonHugePages": "0 kB",
        "ShmemHugePages": "0 kB",
        "ShmemPmdMapped": "0 kB",
        "FileHugePages": "0 kB",
        "FilePmdMapped": "0 kB",
        "Unaccepted": "0 kB",
        "HugePages_Total": "0",
        "HugePages_Free": "0",
        "HugePages_Rsvd": "0",
        "HugePages_Surp": "0",
        "Hugepagesize": "2048 kB",
        "Hugetlb": "0 kB",
        "DirectMap4k": "162220 kB",
        "DirectMap2M": "8157184 kB",
        "DirectMap1G": "255852544 kB"
    },
    "host_memory_GB": [
        1239.222713470459,
        0.0,
        0.0,
        0.0,
        0.0
    ],
    "data_size_per_host_GB": 1279.9931843957586,
    "epochs": 5,
    "end": "2024-09-09T10:52:37.610727"
}