{
    "1": {
        "start": "2024-08-05T21:14:53.833846",
        "block1": {
            "start": "2024-08-05T21:15:05.775101",
            "end": "2024-08-05T21:21:49.938601",
            "duration": "404.16"
        },
        "end": "2024-08-05T21:21:53.317866",
        "duration": "419.48"
    },
    "2": {
        "start": "2024-08-05T21:21:53.321045",
        "block1": {
            "start": "2024-08-05T21:22:04.802067",
            "end": "2024-08-05T21:29:20.613748",
            "duration": "435.81"
        },
        "end": "2024-08-05T21:29:24.254542",
        "duration": "450.93"
    },
    "3": {
        "start": "2024-08-05T21:29:24.256697",
        "block1": {
            "start": "2024-08-05T21:29:36.448667",
            "end": "2024-08-05T21:36:57.201146",
            "duration": "440.75"
        },
        "end": "2024-08-05T21:37:00.511547",
        "duration": "456.25"
    },
    "4": {
        "start": "2024-08-05T21:37:00.517665",
        "block1": {
            "start": "2024-08-05T21:37:12.666930",
            "end": "2024-08-05T21:44:29.141248",
            "duration": "436.47"
        },
        "end": "2024-08-05T21:44:32.734183",
        "duration": "452.22"
    },
    "5": {
        "start": "2024-08-05T21:44:32.738011",
        "block1": {
            "start": "2024-08-05T21:44:44.150756",
            "end": "2024-08-05T21:52:21.191460",
            "duration": "457.04"
        },
        "end": "2024-08-05T21:52:24.292217",
        "duration": "471.55"
    }
}